{"v":"5.8.1","fr":60,"ip":0,"op":20,"w":300,"h":300,"nm":"Comp 7","ddd":0,"assets":[],"layers":[{"ddd":0,"ind":1,"ty":4,"nm":"icon","sr":1,"ks":{"o":{"a":0,"k":100,"ix":11},"r":{"a":1,"k":[{"i":{"x":[0.4],"y":[1]},"o":{"x":[0.6],"y":[0]},"t":0,"s":[0]},{"t":19,"s":[-90]}],"ix":10},"p":{"a":1,"k":[{"i":{"x":0.4,"y":1},"o":{"x":0.6,"y":0},"t":0,"s":[150,150,0],"to":[0,0,0],"ti":[0,0,0]},{"i":{"x":0.4,"y":1},"o":{"x":0.6,"y":0},"t":12,"s":[150,178,0],"to":[0,0,0],"ti":[0,0,0]},{"t":19,"s":[150,150,0]}],"ix":2,"l":2},"a":{"a":0,"k":[150,150,0],"ix":1,"l":2},"s":{"a":0,"k":[100,100,100],"ix":6,"l":2}},"ao":0,"shapes":[{"ty":"gr","it":[{"ind":0,"ty":"sh","ix":1,"ks":{"a":0,"k":{"i":[[0,0],[0,0]],"o":[[0,0],[0,0]],"v":[[176.7,163.3],[220,163.3]],"c":false},"ix":2},"nm":"Path 1","mn":"ADBE Vector Shape - Group","hd":false},{"ty":"tm","s":{"a":1,"k":[{"i":{"x":[0.4],"y":[1]},"o":{"x":[0.6],"y":[0]},"t":0,"s":[0]},{"t":12,"s":[100]}],"ix":1},"e":{"a":0,"k":100,"ix":2},"o":{"a":0,"k":0,"ix":3},"m":1,"ix":2,"nm":"Trim Paths 1","mn":"ADBE Vector Filter - Trim","hd":false},{"ty":"st","c":{"a":0,"k":[0.592156862745,0.592156862745,0.592156862745,1],"ix":3},"o":{"a":0,"k":100,"ix":4},"w":{"a":0,"k":13.3,"ix":5},"lc":2,"lj":1,"ml":10,"bm":0,"nm":"Stroke 1","mn":"ADBE Vector Graphic - Stroke","hd":false},{"ty":"tr","p":{"a":0,"k":[0,0],"ix":2},"a":{"a":0,"k":[0,0],"ix":1},"s":{"a":0,"k":[100,100],"ix":3},"r":{"a":0,"k":0,"ix":6},"o":{"a":0,"k":100,"ix":7},"sk":{"a":0,"k":0,"ix":4},"sa":{"a":0,"k":0,"ix":5},"nm":"Transform"}],"nm":"Group 1","np":3,"cix":2,"bm":0,"ix":1,"mn":"ADBE Vector Group","hd":false},{"ty":"gr","it":[{"ind":0,"ty":"sh","ix":1,"ks":{"a":0,"k":{"i":[[0,0],[0,0],[-2.606,-0.912],[-0.503,-1.436],[0,0]],"o":[[0,0],[0.912,-2.606],[1.436,0.503],[0,0],[0,0]],"v":[[-35,45.248],[-4.719,-41.268],[1.652,-44.336],[4.719,-41.268],[35,45.248]],"c":false},"ix":2},"nm":"Path 1","mn":"ADBE Vector Shape - Group","hd":false},{"ty":"tm","s":{"a":1,"k":[{"i":{"x":[0.4],"y":[1]},"o":{"x":[0.6],"y":[0]},"t":0,"s":[0]},{"t":14,"s":[100]}],"ix":1},"e":{"a":0,"k":100,"ix":2},"o":{"a":0,"k":0,"ix":3},"m":1,"ix":2,"nm":"Trim Paths 1","mn":"ADBE Vector Filter - Trim","hd":false},{"ty":"st","c":{"a":0,"k":[0.592156862745,0.592156862745,0.592156862745,1],"ix":3},"o":{"a":0,"k":100,"ix":4},"w":{"a":0,"k":13.3,"ix":5},"lc":2,"lj":2,"bm":0,"nm":"Stroke 1","mn":"ADBE Vector Graphic - Stroke","hd":false},{"ty":"tr","p":{"a":0,"k":[198.3,144.752],"ix":2},"a":{"a":0,"k":[0,0],"ix":1},"s":{"a":0,"k":[100,100],"ix":3},"r":{"a":0,"k":0,"ix":6},"o":{"a":0,"k":100,"ix":7},"sk":{"a":0,"k":0,"ix":4},"sa":{"a":0,"k":0,"ix":5},"nm":"Transform"}],"nm":"Group 2","np":3,"cix":2,"bm":0,"ix":2,"mn":"ADBE Vector Group","hd":false},{"ty":"gr","it":[{"ind":0,"ty":"sh","ix":1,"ks":{"a":1,"k":[{"i":{"x":0.4,"y":1},"o":{"x":0.6,"y":0},"t":0,"s":[{"i":[[0,0],[0,0],[0,0]],"o":[[0,0],[0,0],[0,0]],"v":[[-17.5,35],[17.5,0],[-17.5,-35]],"c":false}]},{"t":19,"s":[{"i":[[0,0],[0,0],[0,0]],"o":[[0,0],[0,0],[0,0]],"v":[[4.2,60],[64.2,0],[4.2,-60]],"c":false}]}],"ix":2},"nm":"Path 1","mn":"ADBE Vector Shape - Group","hd":false},{"ty":"st","c":{"a":0,"k":[0.592156862745,0.592156862745,0.592156862745,1],"ix":3},"o":{"a":0,"k":100,"ix":4},"w":{"a":1,"k":[{"i":{"x":[0.4],"y":[1]},"o":{"x":[0.6],"y":[0]},"t":0,"s":[13.3]},{"t":19,"s":[16.7]}],"ix":5},"lc":2,"lj":2,"bm":0,"nm":"Stroke 1","mn":"ADBE Vector Graphic - Stroke","hd":false},{"ty":"tr","p":{"a":0,"k":[115.8,150],"ix":2},"a":{"a":0,"k":[0,0],"ix":1},"s":{"a":0,"k":[100,100],"ix":3},"r":{"a":0,"k":0,"ix":6},"o":{"a":0,"k":100,"ix":7},"sk":{"a":0,"k":0,"ix":4},"sa":{"a":0,"k":0,"ix":5},"nm":"Transform"}],"nm":"Group 3","np":2,"cix":2,"bm":0,"ix":3,"mn":"ADBE Vector Group","hd":false},{"ty":"gr","it":[{"ind":0,"ty":"sh","ix":1,"ks":{"a":1,"k":[{"i":{"x":0.4,"y":1},"o":{"x":0.6,"y":0},"t":0,"s":[{"i":[[0,0],[0,0]],"o":[[0,0],[0,0]],"v":[[63.3,150],[130,150]],"c":false}]},{"t":19,"s":[{"i":[[0,0],[0,0]],"o":[[0,0],[0,0]],"v":[[93.3,150],[160,150]],"c":false}]}],"ix":2},"nm":"Path 1","mn":"ADBE Vector Shape - Group","hd":false},{"ty":"tm","s":{"a":1,"k":[{"i":{"x":[0.4],"y":[1]},"o":{"x":[0.6],"y":[0]},"t":0,"s":[0]},{"t":12,"s":[100]}],"ix":1},"e":{"a":0,"k":100,"ix":2},"o":{"a":0,"k":0,"ix":3},"m":1,"ix":2,"nm":"Trim Paths 1","mn":"ADBE Vector Filter - Trim","hd":false},{"ty":"st","c":{"a":0,"k":[0.592156862745,0.592156862745,0.592156862745,1],"ix":3},"o":{"a":0,"k":100,"ix":4},"w":{"a":0,"k":13.3,"ix":5},"lc":2,"lj":1,"ml":10,"bm":0,"nm":"Stroke 1","mn":"ADBE Vector Graphic - Stroke","hd":false},{"ty":"tr","p":{"a":0,"k":[0,0],"ix":2},"a":{"a":0,"k":[0,0],"ix":1},"s":{"a":0,"k":[100,100],"ix":3},"r":{"a":0,"k":0,"ix":6},"o":{"a":0,"k":100,"ix":7},"sk":{"a":0,"k":0,"ix":4},"sa":{"a":0,"k":0,"ix":5},"nm":"Transform"}],"nm":"Group 4","np":3,"cix":2,"bm":0,"ix":4,"mn":"ADBE Vector Group","hd":false}],"ip":0,"op":20,"st":0,"bm":0}],"markers":[]}